app/__init__.py
app/entity/__init__.py
app/entity/plan.py
app/entity/task.py
app/use_case/__init__.py
app/use_case/create_plan.py
app/use_case/create_task.py
app/use_case/event_loop.py
cli/__init__.py
cli/alerter.py
cli/config.py
cli/enigma_machine.py
cli/main.py
cli/nest_client.py
cli/repository_factory.py
cli/command/__init__.py
cli/command/create_plan.py
cli/command/create_task.py
cli/command/event_loop.py
repository/__init__.py
repository/nest_gateway.py
repository/plan.py
repository/task.py
fledgling-0.0.1.dist-info/LICENSE
fledgling-0.0.1.dist-info/METADATA
fledgling-0.0.1.dist-info/WHEEL
fledgling-0.0.1.dist-info/top_level.txt
fledgling-0.0.1.dist-info/RECORD
