Metadata-Version: 2.1
Name: fledgling
Version: 0.0.1
Summary: Client of nest
Home-page: https://github.com/Liutos/fledgling
Author: Liutos
Author-email: mat.liutos@gmail.com
License: UNKNOWN
Project-URL: Bug Tracker, https://github.com/Liutos/fledgling/issues
Platform: UNKNOWN
Classifier: Programming Language :: Python :: 3
Classifier: License :: OSI Approved :: MIT License
Classifier: Operating System :: OS Independent
Requires-Python: >=3.6
